qq_3_toolbox/__init__.py
qq_3_toolbox/problem1_execution_system.py
qq_3_toolbox/problem1_trading_params.py
qq_3_toolbox/problem2_execution_system.py
qq_3_toolbox/problem2_trading_params.py
qq_3_toolbox-0.0.3.dist-info/LICENSE
qq_3_toolbox-0.0.3.dist-info/METADATA
qq_3_toolbox-0.0.3.dist-info/WHEEL
qq_3_toolbox-0.0.3.dist-info/top_level.txt
qq_3_toolbox-0.0.3.dist-info/RECORD
