Metadata-Version: 2.1
Name: qq-3-toolbox
Version: 0.0.3
Summary: Toolbox for QQ3
Home-page: https://github.com/pypa/sampleproject
Author: Auquan
Author-email: qqadmins@auquan.com
License: UNKNOWN
Platform: UNKNOWN
Classifier: Programming Language :: Python :: 3
Classifier: License :: OSI Approved :: MIT License
Classifier: Operating System :: OS Independent
